Workbook

Sheet Raw_data
A1: Column1 | B1: Column2 | C1: Column3 | D1: Column4 | E1: Column5 | F1: Column6 | G1: Column7 | H1: Column8 | I1: Column9 | J1: Column10 | K1: Column11 | L1: Column12 | M1: Column13 | N1: Column14 | O1: Column15 | P1: Column16 | Q1: Column17
A2: BATCH ID | B2: DRUG NAME | C2: BASE COST | D2: API COST | E2: PACKAGING COST | F2: UNITS PRODUCED | G2: SELLING PRICE/UNIT | H2: POTENCY % | I2: TOTAL MANUFACTURING COST | J2: COST PER UNIT | K2: REVENUE | L2: PROFIT | M2: PROFIT MARGIN % | N2: Quality grade | O2: BATCH STATUS | P2: MANUFACTURING YEAR | Q2: BATCH CODE
A3: BATCH-2026-A1 | B3: Paracetamol | C3: 5000 | D3: 1200 | E3: 600 | F3: 10000 | G3: 2.5 | H3: 0.985 | I3: =SUM(D3,E3,C3) -> 6800 | J3: =I3/F3 -> 0.68 | K3: =F3*G3 -> 25000 | L3: =K3-I3 -> 18200 | M3: =L3/K3*100 -> 72.8 | N3: =IF(H3>=0.98, "A", IF(H3>=0.95, "B", "C")) -> A | O3: =IF(AND(H3>0.95, L3>0), "Approved", "Rejected") -> Approved | P3: =MID(A3, FIND("-",A3)+1, 4) -> 2026 | Q3: =RIGHT(A3, LEN(A3) - FIND("-", A3, "7")) -> A1
A4: BATCH-2026-B2 | B4: Amoxicillin | C4: 8500 | D4: 2500 | E4: 900 | F4: 12000 | G4: 3.8 | H4: 0.942 | I4: =SUM(D4,E4,C4) -> 11900 | J4: =I4/F4 -> 0.99166667 | K4: =F4*G4 -> 45600 | L4: =K4-I4 -> 33700 | M4: =L4/K4*100 -> 73.903509 | N4: =IF(H4>=0.98, "A", IF(H4>=0.95, "B", "C")) -> C | O4: =IF(AND(H4>0.95, L4>0), "Approved", "Rejected") -> Rejected | P4: =MID(A4, FIND("-",A4)+1, 4) -> 2026 | Q4: =RIGHT(A4, LEN(A4) - FIND("-", A4, "7")) -> B2
A5: BATCH-2026-C3 | B5: Ibuprofen | C5: 4200 | D5: 900 | E5: 500 | F5: 9000 | G5: 2.2 | H5: 0.961 | I5: =SUM(D5,E5,C5) -> 5600 | J5: =I5/F5 -> 0.62222222 | K5: =F5*G5 -> 19800 | L5: =K5-I5 -> 14200 | M5: =L5/K5*100 -> 71.717172 | N5: =IF(H5>=0.98, "A", IF(H5>=0.95, "B", "C")) -> B | O5: =IF(AND(H5>0.95, L5>0), "Approved", "Rejected") -> Approved | P5: =MID(A5, FIND("-",A5)+1, 4) -> 2026 | Q5: =RIGHT(A5, LEN(A5) - FIND("-", A5, "7")) -> C3
A6: BATCH-2026-D4 | B6: Metformin | C6: 6100 | D6: 1800 | E6: 700 | F6: 15000 | G6: 1.8 | H6: 0.915 | I6: =SUM(D6,E6,C6) -> 8600 | J6: =I6/F6 -> 0.57333333 | K6: =F6*G6 -> 27000 | L6: =K6-I6 -> 18400 | M6: =L6/K6*100 -> 68.148148 | N6: =IF(H6>=0.98, "A", IF(H6>=0.95, "B", "C")) -> C | O6: =IF(AND(H6>0.95, L6>0), "Approved", "Rejected") -> Rejected | P6: =MID(A6, FIND("-",A6)+1, 4) -> 2026 | Q6: =RIGHT(A6, LEN(A6) - FIND("-", A6, "7")) -> D4
A7: BATCH-2026-E5 | B7: Atorvastatin | C7: 9500 | D7: 3100 | E7: 1100 | F7: 18000 | G7: 4.5 | H7: 0.993 | I7: =SUM(D7,E7,C7) -> 13700 | J7: =I7/F7 -> 0.76111111 | K7: =F7*G7 -> 81000 | L7: =K7-I7 -> 67300 | M7: =L7/K7*100 -> 83.08642 | N7: =IF(H7>=0.98, "A", IF(H7>=0.95, "B", "C")) -> A | O7: =IF(AND(H7>0.95, L7>0), "Approved", "Rejected") -> Approved | P7: =MID(A7, FIND("-",A7)+1, 4) -> 2026 | Q7: =RIGHT(A7, LEN(A7) - FIND("-", A7, "7")) -> E5
A8: BATCH-2026-A6 | B8: Aspirin | C8: 4700 | D8: 1000 | E8: 550 | F8: 11000 | G8: 2 | H8: 0.956 | I8: =SUM(D8,E8,C8) -> 6250 | J8: =I8/F8 -> 0.56818182 | K8: =F8*G8 -> 22000 | L8: =K8-I8 -> 15750 | M8: =L8/K8*100 -> 71.590909 | N8: =IF(H8>=0.98, "A", IF(H8>=0.95, "B", "C")) -> B | O8: =IF(AND(H8>0.95, L8>0), "Approved", "Rejected") -> Approved | P8: =MID(A8, FIND("-",A8)+1, 4) -> 2026 | Q8: =RIGHT(A8, LEN(A8) - FIND("-", A8, "7")) -> A6
A9: BATCH-2026-A7 | B9: Omeprazole | C9: 7200 | D9: 2200 | E9: 850 | F9: 14000 | G9: 3.2 | H9: 0.972 | I9: =SUM(D9,E9,C9) -> 10250 | J9: =I9/F9 -> 0.73214286 | K9: =F9*G9 -> 44800 | L9: =K9-I9 -> 34550 | M9: =L9/K9*100 -> 77.120536 | N9: =IF(H9>=0.98, "A", IF(H9>=0.95, "B", "C")) -> B | O9: =IF(AND(H9>0.95, L9>0), "Approved", "Rejected") -> Approved | P9: =MID(A9, FIND("-",A9)+1, 4) -> 2026 | Q9: =RIGHT(A9, LEN(A9) - FIND("-", A9, "7")) -> A7
A10: BATCH-2026-A8 | B10: Azithromycin | C10: 9800 | D10: 3500 | E10: 1200 | F10: 13000 | G10: 5 | H10: 0.948 | I10: =SUM(D10,E10,C10) -> 14500 | J10: =I10/F10 -> 1.1153846 | K10: =F10*G10 -> 65000 | L10: =K10-I10 -> 50500 | M10: =L10/K10*100 -> 77.692308 | N10: =IF(H10>=0.98, "A", IF(H10>=0.95, "B", "C")) -> C | O10: =IF(AND(H10>0.95, L10>0), "Approved", "Rejected") -> Rejected | P10: =MID(A10, FIND("-",A10)+1, 4) -> 2026 | Q10: =RIGHT(A10, LEN(A10) - FIND("-", A10, "7")) -> A8
A11: BATCH-2026-A9 | B11: Cetirizine | C11: 3900 | D11: 800 | E11: 450 | F11: 9500 | G11: 1.9 | H11: 0.987 | I11: =SUM(D11,E11,C11) -> 5150 | J11: =I11/F11 -> 0.54210526 | K11: =F11*G11 -> 18050 | L11: =K11-I11 -> 12900 | M11: =L11/K11*100 -> 71.468144 | N11: =IF(H11>=0.98, "A", IF(H11>=0.95, "B", "C")) -> A | O11: =IF(AND(H11>0.95, L11>0), "Approved", "Rejected") -> Approved | P11: =MID(A11, FIND("-",A11)+1, 4) -> 2026 | Q11: =RIGHT(A11, LEN(A11) - FIND("-", A11, "7")) -> A9
A12: BATCH-2026-A10 | B12: Losartan | C12: 6800 | D12: 2100 | E12: 750 | F12: 12500 | G12: 3 | H12: 0.959 | I12: =SUM(D12,E12,C12) -> 9650 | J12: =I12/F12 -> 0.772 | K12: =F12*G12 -> 37500 | L12: =K12-I12 -> 27850 | M12: =L12/K12*100 -> 74.266667 | N12: =IF(H12>=0.98, "A", IF(H12>=0.95, "B", "C")) -> B | O12: =IF(AND(H12>0.95, L12>0), "Approved", "Rejected") -> Approved | P12: =MID(A12, FIND("-",A12)+1, 4) -> 2026 | Q12: =RIGHT(A12, LEN(A12) - FIND("-", A12, "7")) -> A10
A13: BATCH-2026-A11 | B13: Amlodipine | C13: 5500 | D13: 1600 | E13: 650 | F13: 14500 | G13: 2.4 | H13: 0.963 | I13: =SUM(D13,E13,C13) -> 7750 | J13: =I13/F13 -> 0.53448276 | K13: =F13*G13 -> 34800 | L13: =K13-I13 -> 27050 | M13: =L13/K13*100 -> 77.729885 | N13: =IF(H13>=0.98, "A", IF(H13>=0.95, "B", "C")) -> B | O13: =IF(AND(H13>0.95, L13>0), "Approved", "Rejected") -> Approved | P13: =MID(A13, FIND("-",A13)+1, 4) -> 2026 | Q13: =RIGHT(A13, LEN(A13) - FIND("-", A13, "7")) -> A11
A14: BATCH-2026-A12 | B14: Levocetirizine | C14: 4300 | D14: 950 | E14: 500 | F14: 9800 | G14: 2.1 | H14: 0.977 | I14: =SUM(D14,E14,C14) -> 5750 | J14: =I14/F14 -> 0.58673469 | K14: =F14*G14 -> 20580 | L14: =K14-I14 -> 14830 | M14: =L14/K14*100 -> 72.060253 | N14: =IF(H14>=0.98, "A", IF(H14>=0.95, "B", "C")) -> B | O14: =IF(AND(H14>0.95, L14>0), "Approved", "Rejected") -> Approved | P14: =MID(A14, FIND("-",A14)+1, 4) -> 2026 | Q14: =RIGHT(A14, LEN(A14) - FIND("-", A14, "7")) -> A12
... A52: BATCH-2026-A50 | B52: Montelukast | C52: 7600 | D52: 2450 | E52: 890 | F52: 14100 | G52: 3.7 | H52: 0.976 | I52: =SUM(D52,E52,C52) -> 10940 | J52: =I52/F52 -> 0.77588652 | K52: =F52*G52 -> 52170 | L52: =K52-I52 -> 41230 | M52: =L52/K52*100 -> 79.030094 | N52: =IF(H52>=0.98, "A", IF(H52>=0.95, "B", "C")) -> B | O52: =IF(AND(H52>0.95, L52>0), "Approved", "Rejected") -> Approved | P52: =MID(A52, FIND("-",A52)+1, 4) -> 2026 | Q52: =RIGHT(A52, LEN(A52) - FIND("-", A52, "7")) -> A50
Q53: =RIGHT(A53, 2)
Q54: =RIGHT(A54, 2)

Sheet Dashboard 
A1: PHARMACEUTICAL MANUFACTURING DASHBOARD
G3: (ENTER BATCH NO. HERE)
A4: A | B4: B | F4: Enter Batch ID- | G4: Batch-2026-B2
A5: TOTAL BATCHES | B5: =COUNTA(Raw_data!A3:A52) -> 50
A6: APPROVED BATCHES | B6: =COUNTIF(Raw_data!O3:O52,"Approved") -> 41 | F6: Drug name | G6: =IFERROR(INDEX(Raw_data!B:B,MATCH(G4,Raw_data!A:A,0)),"Not Found") -> Amoxicillin
A7: REJECTED BATCHES | B7: =COUNTIF(Raw_data!O3:O52,"Rejected") -> 9 | F7: Profit | G7: =IFERROR(INDEX(Raw_data!L:L,MATCH(G4,Raw_data!A:A,0)),"Not Found") -> 33700
A8: AVERAGE POTENCY | B8: =AVERAGE(Raw_data!H3:H52) -> 0.96648 | F8: Status | G8: =IFERROR(INDEX(Raw_data!O:O,MATCH(G4,Raw_data!A:A,0)),"Not Found") -> Rejected
A9: TOTAL REVENUE | B9: =SUM(Raw_data!K3:K52) -> 2453340
A10: TOTAL PROFIT | B10: =SUM(Raw_data!L3:L52) -> 1945190
A11: BEST PERFORMING DRUG | B11: =INDEX(Raw_data!B3:B52,MATCH(MAX(Raw_data!L3:L52),Raw_data!L3:L52,0)) -> Jardiance
A14: TOP 5 MOST PROFITABLE DRUGS
A15: Drug name | B15: Profit
A16: =INDEX(Raw_data!B3:B52, MATCH(LARGE(Raw_data!L3:L52,1), Raw_data!L3:L52,0)) -> Jardiance | B16: =LARGE(Raw_data!L3:L52,1) -> 91400
A17: =INDEX(Raw_data!B3:B52, MATCH(LARGE(Raw_data!L3:L52,2), Raw_data!L3:L52,0)) -> Pregabalin | B17: =LARGE(Raw_data!L4:L53,2) -> 75200
A18: =INDEX(Raw_data!B3:B52, MATCH(LARGE(Raw_data!L3:L52,3), Raw_data!L3:L52,0)) -> Rosuvastatin | B18: =LARGE(Raw_data!L5:L54,3) -> 73650
A19: =INDEX(Raw_data!B3:B52, MATCH(LARGE(Raw_data!L3:L52,4), Raw_data!L3:L52,0)) -> Ketamine | B19: =LARGE(Raw_data!L6:L55,4) -> 71820
A20: =INDEX(Raw_data!B3:B52, MATCH(LARGE(Raw_data!L3:L52,5), Raw_data!L3:L52,0)) -> Atorvastatin | B20: =LARGE(Raw_data!L7:L56,5) -> 67300
A42: Status | B42: Count
A43: Approved | B43: =COUNTIF(Raw_data!O3:O52, "Approved") -> 41
A44: Rejected | B44: =COUNTIF(Raw_data!O3:O52,"Rejected") -> 9
